{
    "brand": "Audi",
    "model": "A3",
    "generation": "8P, 8PA \u00b7 \u0420\u0435\u0441\u0442\u0430\u0439\u043b\u0438\u043d\u0433",
    "year": "2008",
    "engine_capacity": "1.6",
    "engine_type": "\u0431\u0435\u043d\u0437\u0438\u043d",
    "transmission_type": "\u0430\u0432\u0442\u043e\u043c\u0430\u0442",
    "generation_with_years": "8P, 8PA \u00b7 \u0420\u0435\u0441\u0442\u0430\u0439\u043b\u0438\u043d\u0433 (2004 - 2008)",
    "interior_color": "\u0442\u0451\u043c\u043d\u044b\u0439",
    "interior_material": "\u0442\u043a\u0430\u043d\u044c",
    "body_type": "\u0445\u044d\u0442\u0447\u0431\u0435\u043a 3 \u0434\u0432.",
    "drive_type": "\u043f\u0435\u0440\u0435\u0434\u043d\u0438\u0439 \u043f\u0440\u0438\u0432\u043e\u0434",
    "color": "\u043a\u0440\u0430\u0441\u043d\u044b\u0439",
    "mileage_km": 230826,
    "condition": "\u0441 \u043f\u0440\u043e\u0431\u0435\u0433\u043e\u043c",
    "price_amount_usd": 8000,
    "locationName": "\u0413\u043e\u043c\u0435\u043b\u044c",
    "sellerName": "\u0421\u0435\u0440\u0433\u0435\u0439",
    "refreshedAt": "2024-06-05T05:59:31+0000",
    "publishedAt": "2024-05-18T09:43:09+0000",
    "publicUrl": "https://cars.av.by/audi/a3/109159843",
    "price_byn": 25414,
    "price_usd": 8000,
    "name_todo": "109159843"
}