{
    "brand": "Peugeot",
    "model": "5008",
    "generation": "I",
    "year": "2013",
    "engine_capacity": "1.6",
    "engine_type": "\u0434\u0438\u0437\u0435\u043b\u044c",
    "transmission_type": "\u043c\u0435\u0445\u0430\u043d\u0438\u043a\u0430",
    "generation_with_years": "I (2009 - 2013)",
    "interior_color": "\u043a\u043e\u043c\u0431\u0438",
    "interior_material": "\u0442\u043a\u0430\u043d\u044c",
    "body_type": "\u043c\u0438\u043d\u0438\u0432\u044d\u043d",
    "drive_type": "\u043f\u0435\u0440\u0435\u0434\u043d\u0438\u0439 \u043f\u0440\u0438\u0432\u043e\u0434",
    "color": "\u0441\u0435\u0440\u0435\u0431\u0440\u0438\u0441\u0442\u044b\u0439",
    "mileage_km": 205900,
    "condition": "\u0441 \u043f\u0440\u043e\u0431\u0435\u0433\u043e\u043c",
    "price_amount_usd": 11950,
    "locationName": "\u041f\u043e\u043b\u043e\u0446\u043a, \u0412\u0438\u0442\u0435\u0431\u0441\u043a\u0430\u044f \u043e\u0431\u043b.",
    "sellerName": "\u0410\u0432\u0442\u043e\u0441\u0430\u043b\u043e\u043d-Autohouse",
    "refreshedAt": "2024-06-05T11:50:42+0000",
    "publishedAt": "2024-05-30T11:21:13+0000",
    "publicUrl": "https://cars.av.by/peugeot/5008/109330381",
    "price_byn": 37963,
    "price_usd": 11950,
    "name_todo": "109330381"
}